twobee/__init__.py
twobee/__main__.py
twobee/py.typed
twobee/chui/__init__.py
twobee/chui/app.py
twobee/chui/screens/__init__.py
twobee/chui/screens/main.py
twobee/chui/widgets/__init__.py
twobee/chui/widgets/bases.py
twobee/lib/__init__.py
twobee/lib/bases.py
twobee/lib/block.py
twobee/lib/file_reader.py
twobee/lib/reader.py
twobee/lib/reader_protocol.py
twobee/lib/sequence.py
twobee/lib/sequence_protocol.py
twobee-0.0.2.dist-info/METADATA
twobee-0.0.2.dist-info/WHEEL
twobee-0.0.2.dist-info/entry_points.txt
twobee-0.0.2.dist-info/top_level.txt
twobee-0.0.2.dist-info/RECORD
