Metadata-Version: 2.1
Name: twobee
Version: 0.0.2
Summary: A simple 2bit file viewer and reader library, built for and with Textual.
Home-page: https://github.com/davep/twobee
Author: Dave Pearson
Author-email: davep@davep.org
Maintainer: Dave Pearson
Maintainer-email: davep@davep.org
License: License :: OSI Approved :: MIT License
Project-URL: Documentation, https://github.com/davep/twobee/blob/main/README.md
Project-URL: Source, https://github.com/davep/twobee
Project-URL: Issues, https://github.com/davep/twobee/issues
Project-URL: Discussions, https://github.com/davep/twobee/discussions
Keywords: terminal,library,2bit,dna,bioinformatics,viewer
Platform: UNKNOWN
Classifier: License :: OSI Approved :: MIT License
Classifier: Environment :: Console
Classifier: Development Status :: 3 - Alpha
Classifier: Intended Audience :: Developers
Classifier: Intended Audience :: Science/Research
Classifier: Operating System :: OS Independent
Classifier: Programming Language :: Python :: 3.7
Classifier: Programming Language :: Python :: 3.8
Classifier: Programming Language :: Python :: 3.9
Classifier: Programming Language :: Python :: 3.10
Classifier: Programming Language :: Python :: 3.11
Classifier: Topic :: Scientific/Engineering :: Bio-Informatics
Classifier: Topic :: Terminals
Classifier: Topic :: Utilities
Classifier: Topic :: Software Development :: Libraries
Classifier: Typing :: Typed
Requires-Python: >=3.7
Requires-Dist: textual (==0.13.0)
